{
  "/* BANKING OPERATIONS */": "/* COMMENTS AREN'T PART OF JSON, JUST FOR READABILITY */",
  "BANK_DEPOSIT_ALL": "banking",
  "BANK_DEPOSIT_ALL_EXCEPT": "banking",
  "BANK_DEPOSIT_INVENTORY_ITEM": "banking",
  "BANK_WITHDRAW_ITEM": "banking",
  "BANK_WITHDRAW_ITEM_AMOUNT": "banking",
  "BANK_WITHDRAW_ITEM_AMOUNT_EXACT": "banking",
  "BANK_WITHDRAW_ALL_ITEM": "banking",
  "BANK_WITHDRAW_NOTED_ITEM": "banking",
  "BANK_WITHDRAW_NOTED_ITEM_AMOUNT": "banking",
  "BANK_CLOSE": "banking",
  "BANK_OPEN": "banking",
  "BANK_SET_PIN": "banking",
  "BANK_FIND_ITEM": "banking",
  "BANK_DEPOSIT_EQUIPMENT": "banking",
  "BANK_CHECK_ITEM_COUNT": "banking",
  "OPEN_BANK": "banking",
  "CLOSE_BANK": "banking",
  "WALK_TO_BANK": "banking",
  "WALK_FULLY_TO_NEAREST_BANK_WITH_TELEPORTS": "banking",
  "WALK_FULLY_TO_NEAREST_BANK": "banking",
  "WITHDRAW_ALL_AS_ITEM": "banking",
  "WITHDRAW_ALL_AS_NOTE": "banking",
  
  "/* UI INTERACTIONS */": "/* COMMENTS AREN'T PART OF JSON, JUST FOR READABILITY */",
  "WIDGET_INTERACT": "widget",
  "WIDGET_GET_CHILDREN": "widget",
  "WIDGET_INTERACT_ITEM": "widget",
  "WIDGET_INTERACT_TEXT": "widget",
  "WIDGET_GET_TEXT": "widget",
  "WIDGET_GET_HIDDEN_STATUS": "widget",
  "WIDGET_COMPONENT_CLICK": "widget",
  "WIDGET_SELECT_OPTION": "widget",
  "DIALOG_HANDLE": "widget",
  "DIALOG_HANDLE_CONTINUE": "widget",
  "DIALOG_HANDLE_OPTION": "widget",
  "DIALOG_CHAT_CONTINUE": "widget",
  "DIALOG_CHAT_OPTION": "widget",
  "DIALOG_NPC": "widget",
  "DIALOG_CHECK_TALKING": "widget",
  
  "/* VARIABLE HANDLING */": "/* COMMENTS AREN'T PART OF JSON, JUST FOR READABILITY */",
  "SET_VARIABLE": "variables_list",
  "CREATE_VARIABLE": "variables_list",
  "GET_VARIABLE": "variables_list",
  "DELETE_VARIABLE": "variables_list",
  "INCREMENT_VARIABLE": "variables_list",
  "DECREMENT_VARIABLE": "variables_list",
  "CREATE_LIST": "variables_list",
  "ADD_TO_LIST": "variables_list",
  "REMOVE_FROM_LIST": "variables_list",
  "CLEAR_LIST": "variables_list",
  "CHECK_LIST_CONTAINS": "variables_list",
  "GET_LIST_SIZE": "variables_list",
  "GET_LIST_ITEM": "variables_list",
  "REPLACE_LIST_ITEM": "variables_list",
  "GET_RANDOM_LIST_ITEM": "variables_list",
  "SORT_LIST": "variables_list",
  "SHUFFLE_LIST": "variables_list",
  "EXPORT_LIST_TO_VARIABLE": "variables_list",
  "EXPORT_VARIABLE_TO_LIST": "variables_list",
  "CREATE_TIMER": "variables_list",
  "CHECK_TIMER": "variables_list",
  "RESTART_TIMER": "variables_list",
  "PAUSE_TIMER": "variables_list",
  "RESUME_TIMER": "variables_list",
  "DELETE_TIMER": "variables_list",
  
  "/* ENTITY INTERACTIONS - PLAYER */": "/* COMMENTS AREN'T PART OF JSON, JUST FOR READABILITY */",
  "PLAYER_INTERACT": "entities_player",
  "PLAYER_GET_NAME": "entities_player",
  "PLAYER_GET_COMBAT_LEVEL": "entities_player",
  "PLAYER_GET_POSITION": "entities_player",
  "PLAYER_GET_ANIMATION": "entities_player",
  "PLAYER_GET_HEALTH": "entities_player",
  "PLAYER_GET_PRAYER": "entities_player",
  "PLAYER_GET_RUN_ENERGY": "entities_player",
  "PLAYER_TOGGLE_RUN": "entities_player",
  "PLAYER_GET_INTERACTING_NPC": "entities_player",
  "PLAYER_GET_INTERACTING_PLAYER": "entities_player",
  "PLAYER_GET_EQUIPMENT": "entities_player",
  "PLAYER_IS_MOVING": "entities_player",
  
  "/* ENTITY INTERACTIONS - NPCS */": "/* COMMENTS AREN'T PART OF JSON, JUST FOR READABILITY */",
  "NPC_INTERACT": "entities_npcs",
  "NPC_GET_NAME": "entities_npcs",
  "NPC_GET_ID": "entities_npcs",
  "NPC_GET_COMBAT_LEVEL": "entities_npcs",
  "NPC_GET_POSITION": "entities_npcs",
  "NPC_GET_HEALTH_PERCENT": "entities_npcs",
  "NPC_GET_ANIMATION": "entities_npcs",
  "NPC_GET_DISTANCE": "entities_npcs",
  "NPC_IS_INTERACTING_WITH_ME": "entities_npcs",
  "NPC_IS_INTERACTING_WITH_PLAYER": "entities_npcs",
  "NPC_FIND_NEAREST": "entities_npcs",
  "NPC_FIND_ALL": "entities_npcs",
  "NPC_COUNT": "entities_npcs",
  
  "/* CONTROL FLOW */": "/* COMMENTS AREN'T PART OF JSON, JUST FOR READABILITY */",
  "IF_BANK_IS_OPEN": "logic",
  "IF_BANK_IS_NOT_OPEN": "logic",
  "IF_INVENTORY_IS_FULL": "logic",
  "IF_INVENTORY_IS_NOT_FULL": "logic",
  "IF_INVENTORY_IS_EMPTY": "logic",
  "IF_INVENTORY_IS_NOT_EMPTY": "logic",
  "IF_INVENTORY_CONTAINS": "logic",
  "IF_INVENTORY_CONTAINS_ALL": "logic",
  "IF_INVENTORY_DOES_NOT_CONTAIN": "logic",
  "IF_EQUIPMENT_CONTAINS": "logic",
  "IF_EQUIPMENT_DOES_NOT_CONTAIN": "logic",
  "IF_GROUND_ITEM_EXISTS": "logic",
  "IF_LOCAL_PLAYER_IS_MOVING": "logic",
  "IF_LOCAL_PLAYER_IS_NOT_MOVING": "logic",
  "IF_LOCAL_PLAYER_IS_ANIMATING": "logic",
  "IF_LOCAL_PLAYER_IS_NOT_ANIMATING": "logic",
  "IF_LOCAL_PLAYER_HEALTH_PERCENTAGE": "logic",
  "IF_LOCAL_PLAYER_PRAYER_PERCENTAGE": "logic",
  "IF_LOCAL_PLAYER_RUN_ENERGY": "logic",
  "IF_IN_COMBAT": "logic",
  "IF_NOT_IN_COMBAT": "logic",
  "IF_OBJECT_EXISTS": "logic",
  "IF_NPC_EXISTS": "logic",
  "IF_PLAYER_EXISTS": "logic",
  "IF_MENU_OPEN": "logic",
  "IF_DIALOG_OPEN": "logic",
  "IF_VARIABLE_EQUALS": "logic",
  "IF_VARIABLE_NOT_EQUALS": "logic",
  "IF_VARIABLE_GREATER_THAN": "logic",
  "IF_VARIABLE_LESS_THAN": "logic",
  "IF_VARIABLE_GREATER_OR_EQUAL": "logic",
  "IF_VARIABLE_LESS_OR_EQUAL": "logic",
  "IF_VARIABLE_CONTAINS": "logic",
  "IF_LIST_CONTAINS": "logic",
  "IF_LIST_EMPTY": "logic",
  "IF_LIST_NOT_EMPTY": "logic",
  "IF_LIST_SIZE": "logic",
  "IF_TIMER_IS_FINISHED": "logic",
  "IF_TIMER_IS_RUNNING": "logic",
  "IF_TIMER_IS_PAUSED": "logic",
  "IF_DISTANCE_TO_POSITION": "logic",
  "IF_DISTANCE_TO_OBJECT": "logic",
  "IF_DISTANCE_TO_NPC": "logic",
  "IF_DISTANCE_TO_PLAYER": "logic",
  "IF_DISTANCE_TO_GROUND_ITEM": "logic",
  "IF_DISTANCE_TO_CLOSEST_BANK_IS": "logic",
  "IF_RANDOM_CHANCE": "logic",
  "IF_BANK_CONTAINS": "logic",
  "IF_FIRST_RUN": "logic",
  "AND_BRANCH": "logic",
  "OR_BRANCH": "logic",
  "WHILE_BANK_IS_OPEN": "logic",
  "WHILE_INVENTORY_CONTAINS": "logic",
  "WHILE_NOT_IN_COMBAT": "logic",
  "WHILE_VARIABLE_EQUALS": "logic",
  "WHILE_VARIABLE_NOT_EQUALS": "logic",
  "WHILE_VARIABLE_GREATER_THAN": "logic",
  "WHILE_VARIABLE_LESS_THAN": "logic",
  "WHILE_TIMER_IS_RUNNING": "logic",
  "LOOP_THROUGH_LIST": "logic",
  "LOOP_N_TIMES": "logic",
  "BREAK": "logic",
  "CONTINUE": "logic",
  "RETURN": "logic",
  "EXIT_SCRIPT": "logic",
  
  "/* TIMING CONTROLS */": "/* COMMENTS AREN'T PART OF JSON, JUST FOR READABILITY */",
  "SLEEP": "sleep",
  "SLEEP_BETWEEN": "sleep",
  "SLEEP_GAUSSIAN": "sleep",
  "SLEEP_NORMAL_DISTRIBUTION": "sleep",
  "SLEEP_UNTIL_CONDITION": "sleep",
  "SLEEP_UNTIL_INVENTORY_CHANGES": "sleep",
  "SLEEP_UNTIL_ANIMATION_ENDS": "sleep",
  "SLEEP_UNTIL_DIALOG_APPEARS": "sleep",
  "SLEEP_UNTIL_DIALOG_CLOSES": "sleep",
  "SLEEP_UNTIL_BANK_OPENS": "sleep",
  "SLEEP_UNTIL_BANK_CLOSES": "sleep",
  "SLEEP_UNTIL_COMBAT_ENDS": "sleep",
  
  "/* GROUND ITEMS */": "/* COMMENTS AREN'T PART OF JSON, JUST FOR READABILITY */",
  "GROUND_ITEM_INTERACT": "entities_ground_items",
  "GROUND_ITEM_GET_NEAREST": "entities_ground_items",
  "GROUND_ITEM_GET_ALL": "entities_ground_items",
  "GROUND_ITEM_GET_AT_POSITION": "entities_ground_items",
  "GROUND_ITEM_COUNT": "entities_ground_items",
  "GROUND_ITEM_PICKUP": "entities_ground_items",
  "GROUND_ITEM_PICKUP_ALL": "entities_ground_items",
  
  "/* MOVEMENT */": "/* COMMENTS AREN'T PART OF JSON, JUST FOR READABILITY */",
  "WALK_TO_POSITION": "walking",
  "WALK_TO_AREA": "walking",
  "WALK_TO_OBJECT": "walking",
  "WALK_TO_NPC": "walking",
  "WALK_TO_PLAYER": "walking",
  "WALK_TO_GROUND_ITEM": "walking",
  "WALK_PATH": "walking",
  "WALK_MINIMAP_POINT": "walking",
  "WALK_SCREEN_POINT": "walking",
  "TELEPORT_TO_VARROCK": "walking",
  "TELEPORT_TO_LUMBRIDGE": "walking",
  "TELEPORT_TO_FALADOR": "walking",
  "TELEPORT_TO_CAMELOT": "walking",
  "TELEPORT_HOME": "walking",
  "TELEPORT_WITH_ITEM": "walking",
  "TELEPORT_WITH_SPELL": "walking",
  
  "/* INVENTORY */": "/* COMMENTS AREN'T PART OF JSON, JUST FOR READABILITY */",
  "INVENTORY_INTERACT_ITEM": "inventory",
  "INVENTORY_USE_ITEM_ON_ITEM": "inventory",
  "INVENTORY_USE_ITEM_ON_OBJECT": "inventory",
  "INVENTORY_USE_ITEM_ON_NPC": "inventory",
  "INVENTORY_USE_ITEM_ON_PLAYER": "inventory",
  "INVENTORY_USE_ITEM_ON_GROUND_ITEM": "inventory",
  "INVENTORY_DROP_ITEM": "inventory",
  "INVENTORY_DROP_ALL": "inventory",
  "INVENTORY_DROP_ALL_EXCEPT": "inventory",
  "INVENTORY_GET_COUNT": "inventory",
  "INVENTORY_GET_COUNT_STACKABLE": "inventory",
  "INVENTORY_ITEM_SLOT": "inventory",
  "INVENTORY_ITEM_ACTION": "inventory",
  "INVENTORY_OPEN": "inventory",
  "INVENTORY_CLOSE": "inventory",
  
  "/* EQUIPMENT */": "/* COMMENTS AREN'T PART OF JSON, JUST FOR READABILITY */",
  "EQUIPMENT_EQUIP_ITEM": "equipment",
  "EQUIPMENT_UNEQUIP_ITEM": "equipment",
  "EQUIPMENT_INTERACT_ITEM": "equipment",
  "EQUIPMENT_CHECK_SLOT": "equipment",
  "EQUIPMENT_GET_ITEM_ID": "equipment",
  "EQUIPMENT_GET_ITEM_COUNT": "equipment",
  "EQUIPMENT_OPEN": "equipment",
  "EQUIPMENT_CLOSE": "equipment",
  
  "/* COMBAT */": "/* COMMENTS AREN'T PART OF JSON, JUST FOR READABILITY */",
  "COMBAT_ATTACK_NPC": "combat",
  "COMBAT_ATTACK_PLAYER": "combat",
  "COMBAT_SET_STYLE": "combat",
  "COMBAT_TOGGLE_AUTO_RETALIATE": "combat",
  "COMBAT_GET_STYLE": "combat",
  "COMBAT_SET_WEAPON_MODE": "combat",
  "COMBAT_EAT_FOOD": "combat",
  "COMBAT_DRINK_POTION": "combat",
  "COMBAT_TOGGLE_SPECIAL_ATTACK": "combat",
  "COMBAT_USE_PRAYER": "combat",
  "COMBAT_TOGGLE_PRAYER": "combat",
  "COMBAT_TOGGLE_QUICK_PRAYER": "combat",
  "COMBAT_CHECK_HEALTH": "combat",
  "COMBAT_CHECK_PRAYER": "combat",
  "COMBAT_CHECK_RUN_ENERGY": "combat",
  
  "/* GAME OBJECTS */": "/* COMMENTS AREN'T PART OF JSON, JUST FOR READABILITY */",
  "GAME_OBJECT_INTERACT": "entities_game_objects",
  "GAME_OBJECT_GET_NEAREST": "entities_game_objects",
  "GAME_OBJECT_GET_ALL": "entities_game_objects",
  "GAME_OBJECT_GET_AT_POSITION": "entities_game_objects",
  "GAME_OBJECT_COUNT": "entities_game_objects",
  "GAME_OBJECT_ACTION": "entities_game_objects",
  "GAME_OBJECT_ID": "entities_game_objects",
  "GAME_OBJECT_NAME": "entities_game_objects",
  "GAME_OBJECT_DISTANCE": "entities_game_objects",
  
  "/* SKILLS AND LEVELING */": "/* COMMENTS AREN'T PART OF JSON, JUST FOR READABILITY */",
  "SKILL_GET_LEVEL": "skills",
  "SKILL_GET_EXPERIENCE": "skills",
  "SKILL_GET_REAL_LEVEL": "skills",
  "SKILL_GET_BOOSTED_LEVEL": "skills",
  "SKILL_GET_EXPERIENCE_TO_LEVEL": "skills",
  "SKILL_GET_PERCENTAGE_TO_LEVEL": "skills",
  "SKILL_TOTAL_LEVEL": "skills",
  "SKILL_TOTAL_EXPERIENCE": "skills",
  
  "/* UTILITIES */": "/* COMMENTS AREN'T PART OF JSON, JUST FOR READABILITY */",
  "LOG": "utilities",
  "DEBUG_LOG": "utilities",
  "ERROR_LOG": "utilities",
  "TAKE_SCREENSHOT": "utilities",
  "RANDOM_NUMBER": "utilities",
  "ROTATE_CAMERA": "utilities",
  "ROTATE_CAMERA_RANDOMLY": "utilities",
  "MOVE_MOUSE_RANDOMLY": "utilities",
  "GET_CURRENT_TIME": "utilities",
  "FORMAT_DATE_TIME": "utilities",
  "CALCULATE_DISTANCE": "utilities",
  "EXECUTE_AFTER_DELAY": "utilities",
  
  "/* ANTI-BAN MEASURES */": "/* COMMENTS AREN'T PART OF JSON, JUST FOR READABILITY */",
  "ANTIBAN_RANDOM_MOUSE_MOVEMENT": "antiban",
  "ANTIBAN_RANDOM_CAMERA_ROTATION": "antiban",
  "ANTIBAN_RANDOM_IDLE": "antiban",
  "ANTIBAN_EXAMINE_ENTITY": "antiban",
  "ANTIBAN_HOVER_PLAYER": "antiban",
  "ANTIBAN_HOVER_NPC": "antiban",
  "ANTIBAN_HOVER_OBJECT": "antiban",
  "ANTIBAN_CHECK_STATS": "antiban",
  "ANTIBAN_OPEN_RANDOM_TAB": "antiban",
  "ANTIBAN_MOVE_RANDOMLY": "antiban",
  "ANTIBAN_BREAK_HANDLER": "antiban",
  
  "/* GRAND EXCHANGE */": "/* COMMENTS AREN'T PART OF JSON, JUST FOR READABILITY */",
  "GE_OPEN": "grand_exchange",
  "GE_CLOSE": "grand_exchange",
  "GE_BUY_ITEM": "grand_exchange",
  "GE_SELL_ITEM": "grand_exchange",
  "GE_COLLECT": "grand_exchange",
  "GE_CHECK_OFFER_STATUS": "grand_exchange",
  "GE_ABORT_OFFER": "grand_exchange",
  "GE_GET_ITEM_PRICE": "grand_exchange",
  
  "/* PRAYER */": "/* COMMENTS AREN'T PART OF JSON, JUST FOR READABILITY */",
  "PRAYER_ACTIVATE": "prayer",
  "PRAYER_DEACTIVATE": "prayer",
  "PRAYER_TOGGLE": "prayer",
  "PRAYER_ACTIVATE_ALL": "prayer",
  "PRAYER_DEACTIVATE_ALL": "prayer",
  "PRAYER_IS_ACTIVE": "prayer",
  "PRAYER_GET_POINTS": "prayer",
  "PRAYER_SET_QUICK_PRAYERS": "prayer",
  "PRAYER_TOGGLE_QUICK_PRAYERS": "prayer",
  
  "/* FARMING */": "/* COMMENTS AREN'T PART OF JSON, JUST FOR READABILITY */",
  "FARMING_CHECK_PATCH_STATE": "farming",
  "FARMING_HARVEST_PATCH": "farming",
  "FARMING_PLANT_SEED": "farming",
  "FARMING_CURE_DISEASE": "farming",
  "FARMING_COMPOST_PATCH": "farming",
  "FARMING_CLEAR_PATCH": "farming",
  "FARMING_GET_GROWTH_STAGE": "farming",
  "FARMING_INTERACT_PATCH": "farming",
  
  "/* CLUE SCROLLS */": "/* COMMENTS AREN'T PART OF JSON, JUST FOR READABILITY */",
  "CLUE_SCROLL_SOLVE_ANAGRAM": "clue_scrolls",
  "CLUE_SCROLL_SOLVE_CRYPTIC": "clue_scrolls",
  "CLUE_SCROLL_SOLVE_COORDINATE": "clue_scrolls",
  "CLUE_SCROLL_SOLVE_EMOTE": "clue_scrolls",
  "CLUE_SCROLL_SOLVE_MAP": "clue_scrolls",
  "CLUE_SCROLL_SOLVE_PUZZLE_BOX": "clue_scrolls",
  "CLUE_SCROLL_DIG": "clue_scrolls",
  
  "/* INTERFACE AND MENU */": "/* COMMENTS AREN'T PART OF JSON, JUST FOR READABILITY */",
  "MENU_CLICK_OPTION": "interface_menu",
  "MENU_GET_OPTIONS": "interface_menu",
  "MENU_IS_OPEN": "interface_menu",
  "MENU_CLOSE": "interface_menu",
  "INTERFACE_CLICK_COMPONENT": "interface_menu",
  "INTERFACE_GET_TEXT": "interface_menu",
  "INTERFACE_GET_HIDDEN_STATUS": "interface_menu",
  "INTERFACE_INPUT_TEXT": "interface_menu",
  "INTERFACE_HANDLE_DIALOG": "interface_menu",
  
  "/* FRIENDS AND CLAN */": "/* COMMENTS AREN'T PART OF JSON, JUST FOR READABILITY */",
  "FRIENDS_ADD": "social",
  "FRIENDS_REMOVE": "social",
  "FRIENDS_IS_FRIEND": "social",
  "FRIENDS_GET_LIST": "social",
  "FRIENDS_SEND_MESSAGE": "social",
  "CLAN_CHAT_JOIN": "social",
  "CLAN_CHAT_LEAVE": "social",
  "CLAN_CHAT_SEND_MESSAGE": "social",
  "CLAN_CHAT_GET_MEMBERS": "social",
  
  "/* MINIGAMES */": "/* COMMENTS AREN'T PART OF JSON, JUST FOR READABILITY */",
  "MINIGAME_GET_STATE": "minigames",
  "MINIGAME_INTERACT": "minigames",
  "MINIGAME_GET_POINTS": "minigames",
  "MINIGAME_START": "minigames",
  "MINIGAME_END": "minigames",
  "MINIGAME_PERFORM_ACTION": "minigames"
}